chunkingman/__init__.py
chunkingman/base_chunker.py
chunkingman/cluster_semantic_chunker.py
chunkingman/fixed_token_chunker.py
chunkingman/kamradt_modified_chunker.py
chunkingman/llm_semantic_chunker.py
chunkingman/recursive_token_chunker.py
chunkingman/utils.py
chunkingman/deprecated/cluster_semantic_chunker.py
chunkingman-0.0.3.dist-info/licenses/LICENSE
chunkingman-0.0.3.dist-info/METADATA
chunkingman-0.0.3.dist-info/WHEEL
chunkingman-0.0.3.dist-info/top_level.txt
chunkingman-0.0.3.dist-info/RECORD
