Metadata-Version: 2.4
Name: chunkingman
Version: 0.0.3
Summary: A library for various text chunking strategies, including token-based, semantic, LLM-guided and hybrid approaches.
Author-email: Román Pérez Dumpert <roman.p98@gmail.com>
License:                                  Apache License
Project-URL: Homepage, https://github.com/romanpert/chunkingman
Project-URL: Repository, https://github.com/romanpert/chunkingman
Project-URL: Issues, https://github.com/romanpert/chunkingman/issues
Keywords: chunking,text-splitting,embeddings,semantic,openai,nlp
Classifier: Programming Language :: Python :: 3
Classifier: License :: OSI Approved :: Apache Software License
Classifier: Operating System :: OS Independent
Requires-Python: >=3.12
License-File: LICENSE
Requires-Dist: rapidfuzz==3.14.0
Requires-Dist: chromadb==1.0.20
Requires-Dist: tiktoken==0.11.0
Requires-Dist: sentence-transformers==5.1.0
Requires-Dist: numpy==2.3.2
Requires-Dist: backoff==2.2.1
Requires-Dist: tqdm==4.67.1
Requires-Dist: openai==1.102.0
Requires-Dist: anthropic==0.64.0
Requires-Dist: attrs==25.3.0
Dynamic: license-file
